buge/main.py
buge-0.0.7.dist-info/LICENSE
buge-0.0.7.dist-info/METADATA
buge-0.0.7.dist-info/WHEEL
buge-0.0.7.dist-info/entry_points.txt
buge-0.0.7.dist-info/top_level.txt
buge-0.0.7.dist-info/RECORD
